[
    {
        "Date": "Mar 22",
        "Day": "Fri",
        "Match": "1st Match",
        "Team 1": "RCB",
        "Team 2": "CSK",
        "Venue": "MA Chidambaram Stadium, Chennai",
        "Result": "CSK won by 6 wkts",
        "Local Time": "08:00 PM",
        "GMT Time": "02:30 PM"
    },
    {
        "Date": "Mar 23",
        "Day": "Sat",
        "Match": "2nd Match",
        "Team 1": "DC",
        "Team 2": "PBK",
        "Venue": "Maharaja Yadavindra Singh International Cricket Stadium, Mullanpur, Chandigarh",
        "Result": "PBK won by 4 wkts",
        "Local Time": "03:30 PM",
        "GMT Time": "10:00 AM"
    },
    {
        "Date": "Mar 23",
        "Day": "Sat",
        "Match": "3rd Match",
        "Team 1": "KKR",
        "Team 2": "SRH",
        "Venue": "Eden Gardens, Kolkata",
        "Result": "KKR won by 4 runs",
        "Local Time": "07:30 PM",
        "GMT Time": "02:00 PM"
    },
    {
        "Date": "Mar 24",
        "Day": "Sun",
        "Match": "4th Match",
        "Team 1": "RR",
        "Team 2": "LSG",
        "Venue": "Sawai Mansingh Stadium, Jaipur",
        "Result": "RR won by 20 runs",
        "Local Time": "03:30 PM",
        "GMT Time": "10:00 AM"
    },
    {
        "Date": "Mar 24",
        "Day": "Sun",
        "Match": "5th Match",
        "Team 1": "GT",
        "Team 2": "MI",
        "Venue": "Narendra Modi Stadium, Ahmedabad",
        "Result": "GT won by 6 runs",
        "Local Time": "07:30 PM",
        "GMT Time": "02:00 PM"
    },
    {
        "Date": "Mar 25",
        "Day": "Mon",
        "Match": "6th Match",
        "Team 1": "RCB",
        "Team 2": "PBK",
        "Venue": "M.Chinnaswamy Stadium, Bengaluru",
        "Result": "Match starts at Mar 25, 14:00 GMT",
        "Local Time": "07:30 PM",
        "GMT Time": "02:00 PM"
    },
    {
        "Date": "Mar 26",
        "Day": "Tue",
        "Match": "7th Match",
        "Team 1": "CSK",
        "Team 2": "GT",
        "Venue": "MA Chidambaram Stadium, Chennai",
        "Result": "Match starts at Mar 26, 14:00 GMT",
        "Local Time": "07:30 PM",
        "GMT Time": "02:00 PM"
    },
    {
        "Date": "Mar 27",
        "Day": "Wed",
        "Match": "8th Match",
        "Team 1": "SRH",
        "Team 2": "MI",
        "Venue": "Rajiv Gandhi International Stadium, Hyderabad",
        "Result": "Match starts at Mar 27, 14:00 GMT",
        "Local Time": "07:30 PM",
        "GMT Time": "02:00 PM"
    },
    {
        "Date": "Mar 28",
        "Day": "Thu",
        "Match": "9th Match",
        "Team 1": "RR",
        "Team 2": "DC",
        "Venue": "Sawai Mansingh Stadium, Jaipur",
        "Result": "Match starts at Mar 28, 14:00 GMT",
        "Local Time": "07:30 PM",
        "GMT Time": "02:00 PM"
    },
    {
        "Date": "Mar 29",
        "Day": "Fri",
        "Match": "10th Match",
        "Team 1": "RCB",
        "Team 2": "KKR",
        "Venue": "M.Chinnaswamy Stadium, Bengaluru",
        "Result": "Match starts at Mar 29, 14:00 GMT",
        "Local Time": "07:30 PM",
        "GMT Time": "02:00 PM"
    },
    {
        "Date": "Mar 30",
        "Day": "Sat",
        "Match": "11th Match",
        "Team 1": "LSG",
        "Team 2": "PBK",
        "Venue": "Bharat Ratna Shri Atal Bihari Vajpayee Ekana Cricket Stadium, Lucknow",
        "Result": "Match starts at Mar 30, 14:00 GMT",
        "Local Time": "07:30 PM",
        "GMT Time": "02:00 PM"
    },
    {
        "Date": "Mar 31",
        "Day": "Sun",
        "Match": "12th Match",
        "Team 1": "GT",
        "Team 2": "SRH",
        "Venue": "Narendra Modi Stadium, Ahmedabad",
        "Result": "Match starts at Mar 31, 10:00 GMT",
        "Local Time": "03:30 PM",
        "GMT Time": "10:00 AM"
    },
    {
        "Date": "Mar 31",
        "Day": "Sun",
        "Match": "13th Match",
        "Team 1": "DC",
        "Team 2": "CSK",
        "Venue": "Dr. Y.S. Rajasekhara Reddy ACA-VDCA Cricket Stadium, Visakhapatnam",
        "Result": "Match starts at Mar 31, 14:00 GMT",
        "Local Time": "07:30 PM",
        "GMT Time": "02:00 PM"
    },
    {
        "Date": "Apr 01",
        "Day": "Mon",
        "Match": "14th Match",
        "Team 1": "MI",
        "Team 2": "RR",
        "Venue": "Wankhede Stadium, Mumbai",
        "Result": "Match starts at Apr 01, 14:00 GMT",
        "Local Time": "07:30 PM",
        "GMT Time": "02:00 PM"
    },
    {
        "Date": "Apr 02",
        "Day": "Tue",
        "Match": "15th Match",
        "Team 1": "RCB",
        "Team 2": "LSG",
        "Venue": "M.Chinnaswamy Stadium, Bengaluru",
        "Result": "Match starts at Apr 02, 14:00 GMT",
        "Local Time": "07:30 PM",
        "GMT Time": "02:00 PM"
    },
    {
        "Date": "Apr 03",
        "Day": "Wed",
        "Match": "16th Match",
        "Team 1": "DC",
        "Team 2": "KKR",
        "Venue": "Dr. Y.S. Rajasekhara Reddy ACA-VDCA Cricket Stadium, Visakhapatnam",
        "Result": "Match starts at Apr 03, 14:00 GMT",
        "Local Time": "07:30 PM",
        "GMT Time": "02:00 PM"
    },
    {
        "Date": "Apr 04",
        "Day": "Thu",
        "Match": "17th Match",
        "Team 1": "GT",
        "Team 2": "PBK",
        "Venue": "Narendra Modi Stadium, Ahmedabad",
        "Result": "Match starts at Apr 04, 14:00 GMT",
        "Local Time": "07:30 PM",
        "GMT Time": "02:00 PM"
    },
    {
        "Date": "Apr 05",
        "Day": "Fri",
        "Match": "18th Match",
        "Team 1": "SRH",
        "Team 2": "CSK",
        "Venue": "Rajiv Gandhi International Stadium, Hyderabad",
        "Result": "Match starts at Apr 05, 14:00 GMT",
        "Local Time": "07:30 PM",
        "GMT Time": "02:00 PM"
    },
    {  
        "Day": "Sat",
        "Match": "19th Match",
        "Team 1": "RR",
        "Team 2": "RCB",
        "Venue": "Sawai Mansingh Stadium, Jaipur",
        "Result": "Match starts at Apr 06, 14:00 GMT",
        "Local Time": "07:30 PM",
        "GMT Time": "02:00 PM"
    }

]
